{
  "id": "3028",
  "title": "International friendly",
  "startTime": "2003-02-12T18:15:00",
  "channel": "belgianfootball",
  "category": "Belgian Red Devils",
  "location": {
    "name": null,
    "city": "Annaba"
  },
  "officials": [],
  "events": [
    {
      "minute": 91,
      "home": [
        {
          "lastName": "Belmadi",
          "firstName": null,
          "teamId": "667",
          "kind": "goalScored",
          "minute": 91
        }
      ],
      "away": []
    },
    {
      "minute": 85,
      "home": [],
      "away": [
        {
          "lastName": "Soetaers",
          "firstName": "Tom",
          "teamId": "578",
          "kind": "minuteIn",
          "minute": 85
        },
        {
          "lastName": "Goor",
          "firstName": "Bart",
          "teamId": "578",
          "kind": "minuteOut",
          "minute": 85
        }
      ]
    },
    {
      "minute": 81,
      "home": [],
      "away": [
        {
          "lastName": "Martens",
          "firstName": "Sandy",
          "teamId": "578",
          "kind": "minuteIn",
          "minute": 81
        },
        {
          "lastName": "Buffel",
          "firstName": "Thomas",
          "teamId": "578",
          "kind": "minuteOut",
          "minute": 81
        }
      ]
    },
    {
      "minute": 79,
      "home": [],
      "away": [
        {
          "lastName": "Roussel",
          "firstName": "Cédric",
          "teamId": "578",
          "kind": "minuteIn",
          "minute": 79
        },
        {
          "lastName": "Mpenza",
          "firstName": "Emile",
          "teamId": "578",
          "kind": "minuteOut",
          "minute": 79
        }
      ]
    },
    {
      "minute": 62,
      "home": [
        {
          "lastName": "Akrour",
          "firstName": null,
          "teamId": "667",
          "kind": "minuteIn",
          "minute": 62
        },
        {
          "lastName": "Ammour",
          "firstName": null,
          "teamId": "667",
          "kind": "minuteIn",
          "minute": 62
        },
        {
          "lastName": "Cherrad",
          "firstName": null,
          "teamId": "667",
          "kind": "minuteOut",
          "minute": 62
        },
        {
          "lastName": "Krouche",
          "firstName": null,
          "teamId": "667",
          "kind": "minuteOut",
          "minute": 62
        }
      ],
      "away": []
    },
    {
      "minute": 57,
      "home": [],
      "away": [
        {
          "lastName": "Mpenza",
          "firstName": "Emile",
          "teamId": "578",
          "kind": "goalScored",
          "minute": 57
        }
      ]
    },
    {
      "minute": 54,
      "home": [],
      "away": [
        {
          "lastName": "Mpenza",
          "firstName": "Mbo",
          "teamId": "578",
          "kind": "minuteIn",
          "minute": 54
        },
        {
          "lastName": "Sonck",
          "firstName": "Wesley",
          "teamId": "578",
          "kind": "minuteOut",
          "minute": 54
        }
      ]
    },
    {
      "minute": 46,
      "home": [
        {
          "lastName": "Belkaid",
          "firstName": null,
          "teamId": "667",
          "kind": "minuteIn",
          "minute": 46
        },
        {
          "lastName": "Ziani",
          "firstName": null,
          "teamId": "667",
          "kind": "minuteIn",
          "minute": 46
        },
        {
          "lastName": "Arribi",
          "firstName": null,
          "teamId": "667",
          "kind": "minuteOut",
          "minute": 46
        },
        {
          "lastName": "Saifi",
          "firstName": null,
          "teamId": "667",
          "kind": "minuteOut",
          "minute": 46
        }
      ],
      "away": [
        {
          "lastName": "Herpoel",
          "firstName": "Frédéric",
          "teamId": "578",
          "kind": "minuteIn",
          "minute": 46
        },
        {
          "lastName": "Thijs",
          "firstName": "Bernd",
          "teamId": "578",
          "kind": "minuteIn",
          "minute": 46
        },
        {
          "lastName": "De Vlieger",
          "firstName": "Geert",
          "teamId": "578",
          "kind": "minuteOut",
          "minute": 46
        },
        {
          "lastName": "Van Buyten",
          "firstName": "Daniel",
          "teamId": "578",
          "kind": "minuteOut",
          "minute": 46
        }
      ]
    },
    {
      "minute": 7,
      "home": [],
      "away": [
        {
          "lastName": "Sonck",
          "firstName": "Wesley",
          "teamId": "578",
          "kind": "goalScored",
          "minute": 7
        }
      ]
    },
    {
      "minute": 2,
      "home": [],
      "away": [
        {
          "lastName": "Mpenza",
          "firstName": "Emile",
          "teamId": "578",
          "kind": "goalScored",
          "minute": 2
        }
      ]
    }
  ],
  "homeTeam": {
    "id": "667",
    "name": "Algeria",
    "logo": "https://s3.eu-central-1.amazonaws.com/belgianfootball/s3fs-public/rbfa/img/logos/countries/667.png"
  },
  "awayTeam": {
    "id": "578",
    "name": "Belgium",
    "logo": "https://s3.eu-central-1.amazonaws.com/belgianfootball/s3fs-public/rbfa/img/logos/countries/578.png"
  },
  "outcome": {
    "homeTeamGoals": 1,
    "homeTeamPenaltiesScored": null,
    "awayTeamGoals": 3,
    "awayTeamPenaltiesScored": null,
    "subscript": null,
    "isFinished": true,
    "hasPenalties": false,
    "hasSubscript": false
  },
  "tournament": {
    "ageCategory": "Belgian Red Devils",
    "nameTournament": null,
    "qualifyingGroup": null,
    "groupCode": null
  },
  "lineup": [
    {
      "home": {
        "id": "1Gaouaouinull",
        "lastName": "Gaouaoui",
        "firstName": null,
        "shirtNumber": "1",
        "badges": "(GK)",
        "events": []
      },
      "away": {
        "id": "1661",
        "lastName": "De Vlieger",
        "firstName": "Geert",
        "shirtNumber": "1",
        "badges": "(GK)",
        "events": [
          {
            "type": "minuteOut",
            "minute": 46
          }
        ]
      }
    },
    {
      "home": {
        "id": "2Ghazinull",
        "lastName": "Ghazi",
        "firstName": null,
        "shirtNumber": "2",
        "badges": "",
        "events": []
      },
      "away": {
        "id": "180",
        "lastName": "De Cock",
        "firstName": "Olivier",
        "shirtNumber": "2",
        "badges": "",
        "events": []
      }
    },
    {
      "home": {
        "id": "3Driouchenull",
        "lastName": "Driouche",
        "firstName": null,
        "shirtNumber": "3",
        "badges": "",
        "events": []
      },
      "away": {
        "id": "2617",
        "lastName": "Simons",
        "firstName": "Timmy",
        "shirtNumber": "3",
        "badges": "",
        "events": []
      }
    },
    {
      "home": {
        "id": "4Zeghdoudnull",
        "lastName": "Zeghdoud",
        "firstName": null,
        "shirtNumber": "4",
        "badges": "",
        "events": []
      },
      "away": {
        "id": "130",
        "lastName": "Van Buyten",
        "firstName": "Daniel",
        "shirtNumber": "4",
        "badges": "",
        "events": [
          {
            "type": "minuteOut",
            "minute": 46
          }
        ]
      }
    },
    {
      "home": {
        "id": "5Zarabinull",
        "lastName": "Zarabi",
        "firstName": null,
        "shirtNumber": "5",
        "badges": "",
        "events": []
      },
      "away": {
        "id": "112",
        "lastName": "Van der Heyden",
        "firstName": "Peter",
        "shirtNumber": "5",
        "badges": "",
        "events": []
      }
    },
    {
      "home": {
        "id": "6Arribinull",
        "lastName": "Arribi",
        "firstName": null,
        "shirtNumber": "6",
        "badges": "",
        "events": [
          {
            "type": "minuteOut",
            "minute": 46
          }
        ]
      },
      "away": {
        "id": "340",
        "lastName": "Englebert",
        "firstName": "Gaëtan",
        "shirtNumber": "6",
        "badges": "",
        "events": []
      }
    },
    {
      "home": {
        "id": "7Krouchenull",
        "lastName": "Krouche",
        "firstName": null,
        "shirtNumber": "7",
        "badges": "",
        "events": [
          {
            "type": "minuteOut",
            "minute": 62
          }
        ]
      },
      "away": {
        "id": "260",
        "lastName": "Vanderhaeghe",
        "firstName": "Yves",
        "shirtNumber": "7",
        "badges": "",
        "events": []
      }
    },
    {
      "home": {
        "id": "8Belmadinull",
        "lastName": "Belmadi",
        "firstName": null,
        "shirtNumber": "8",
        "badges": "",
        "events": [
          {
            "type": "goalScored",
            "minute": 91
          }
        ]
      },
      "away": {
        "id": "176",
        "lastName": "Goor",
        "firstName": "Bart",
        "shirtNumber": "8",
        "badges": "",
        "events": [
          {
            "type": "minuteOut",
            "minute": 85
          }
        ]
      }
    },
    {
      "home": {
        "id": "9Mansourinull",
        "lastName": "Mansouri",
        "firstName": null,
        "shirtNumber": "9",
        "badges": "",
        "events": []
      },
      "away": {
        "id": "313",
        "lastName": "Sonck",
        "firstName": "Wesley",
        "shirtNumber": "9",
        "badges": "",
        "events": [
          {
            "type": "goalScored",
            "minute": 7
          },
          {
            "type": "minuteOut",
            "minute": 54
          }
        ]
      }
    },
    {
      "home": {
        "id": "10Saifinull",
        "lastName": "Saifi",
        "firstName": null,
        "shirtNumber": "10",
        "badges": "",
        "events": [
          {
            "type": "minuteOut",
            "minute": 46
          }
        ]
      },
      "away": {
        "id": "1065",
        "lastName": "Buffel",
        "firstName": "Thomas",
        "shirtNumber": "10",
        "badges": "",
        "events": [
          {
            "type": "minuteOut",
            "minute": 81
          }
        ]
      }
    },
    {
      "home": {
        "id": "11Cherradnull",
        "lastName": "Cherrad",
        "firstName": null,
        "shirtNumber": "11",
        "badges": "",
        "events": [
          {
            "type": "minuteOut",
            "minute": 62
          }
        ]
      },
      "away": {
        "id": "404",
        "lastName": "Mpenza",
        "firstName": "Emile",
        "shirtNumber": "11",
        "badges": "",
        "events": [
          {
            "type": "goalScored",
            "minute": 2
          },
          {
            "type": "goalScored",
            "minute": 57
          },
          {
            "type": "minuteOut",
            "minute": 79
          }
        ]
      }
    }
  ],
  "substitutes": [
    {
      "home": {
        "id": "12Belkaidnull",
        "lastName": "Belkaid",
        "firstName": null,
        "shirtNumber": "12",
        "badges": "",
        "events": [
          {
            "type": "minuteIn",
            "minute": 46
          }
        ]
      },
      "away": {
        "id": "1417",
        "lastName": "Herpoel",
        "firstName": "Frédéric",
        "shirtNumber": "12",
        "badges": "",
        "events": [
          {
            "type": "minuteIn",
            "minute": 46
          }
        ]
      }
    },
    {
      "home": {
        "id": "13Zianinull",
        "lastName": "Ziani",
        "firstName": null,
        "shirtNumber": "13",
        "badges": "",
        "events": [
          {
            "type": "minuteIn",
            "minute": 46
          }
        ]
      },
      "away": {
        "id": "379",
        "lastName": "Thijs",
        "firstName": "Bernd",
        "shirtNumber": "13",
        "badges": "",
        "events": [
          {
            "type": "minuteIn",
            "minute": 46
          }
        ]
      }
    },
    {
      "home": {
        "id": "14Akrournull",
        "lastName": "Akrour",
        "firstName": null,
        "shirtNumber": "14",
        "badges": "",
        "events": [
          {
            "type": "minuteIn",
            "minute": 62
          }
        ]
      },
      "away": {
        "id": "1463",
        "lastName": "Mpenza",
        "firstName": "Mbo",
        "shirtNumber": "14",
        "badges": "",
        "events": [
          {
            "type": "minuteIn",
            "minute": 54
          }
        ]
      }
    },
    {
      "home": {
        "id": "15Ammournull",
        "lastName": "Ammour",
        "firstName": null,
        "shirtNumber": "15",
        "badges": "",
        "events": [
          {
            "type": "minuteIn",
            "minute": 62
          }
        ]
      },
      "away": {
        "id": "408",
        "lastName": "Roussel",
        "firstName": "Cédric",
        "shirtNumber": "15",
        "badges": "",
        "events": [
          {
            "type": "minuteIn",
            "minute": 79
          }
        ]
      }
    },
    {
      "home": null,
      "away": {
        "id": "348",
        "lastName": "Martens",
        "firstName": "Sandy",
        "shirtNumber": "16",
        "badges": "",
        "events": [
          {
            "type": "minuteIn",
            "minute": 81
          }
        ]
      }
    },
    {
      "home": null,
      "away": {
        "id": "197",
        "lastName": "Soetaers",
        "firstName": "Tom",
        "shirtNumber": "17",
        "badges": "",
        "events": [
          {
            "type": "minuteIn",
            "minute": 85
          }
        ]
      }
    }
  ],
  "staffLineup": [
    {
      "home": null,
      "away": {
        "lastName": "Snelders",
        "firstName": "Eddy",
        "function": "coach"
      }
    },
    {
      "home": null,
      "away": {
        "lastName": "Anthuenis",
        "firstName": "Aimé",
        "function": "coach"
      }
    }
  ]
}