{
  "id": "8203",
  "title": "FIFA World Cup",
  "startTime": "2014-07-01T22:00:00",
  "channel": "belgianfootball",
  "category": "Belgian Red Devils",
  "location": {
    "name": "Arena Fonte Nova",
    "city": "Salvador"
  },
  "officials": [
    {
      "lastName": "Haimoudi",
      "firstName": "Djamel",
      "function": "referee"
    },
    {
      "lastName": "Achik",
      "firstName": "Redouane",
      "function": "firstAssistantReferee"
    },
    {
      "lastName": "Etchiali",
      "firstName": "Abdelhak",
      "function": "secondAssistantReferee"
    },
    {
      "lastName": "Hauata",
      "firstName": "Norbert",
      "function": "fourthOfficial"
    }
  ],
  "events": [
    {
      "minute": 111,
      "home": [
        {
          "lastName": "Chadli",
          "firstName": "Nacer",
          "teamId": "578",
          "kind": "minuteIn",
          "minute": 111
        },
        {
          "lastName": "Hazard",
          "firstName": "Eden",
          "teamId": "578",
          "kind": "minuteOut",
          "minute": 111
        }
      ],
      "away": []
    },
    {
      "minute": 107,
      "home": [],
      "away": [
        {
          "lastName": "Green",
          "firstName": "Julian",
          "teamId": "647",
          "kind": "goalScored",
          "minute": 107
        }
      ]
    },
    {
      "minute": 105,
      "home": [
        {
          "lastName": "Lukaku",
          "firstName": "Romelu",
          "teamId": "578",
          "kind": "goalScored",
          "minute": 105
        }
      ],
      "away": [
        {
          "lastName": "Green",
          "firstName": "Julian",
          "teamId": "647",
          "kind": "minuteIn",
          "minute": 105
        },
        {
          "lastName": "Bedoya",
          "firstName": "Alejandro",
          "teamId": "647",
          "kind": "minuteOut",
          "minute": 105
        }
      ]
    },
    {
      "minute": 93,
      "home": [
        {
          "lastName": "De Bruyne",
          "firstName": "Kevin",
          "teamId": "578",
          "kind": "goalScored",
          "minute": 93
        }
      ],
      "away": []
    },
    {
      "minute": 91,
      "home": [
        {
          "lastName": "Lukaku",
          "firstName": "Romelu",
          "teamId": "578",
          "kind": "minuteIn",
          "minute": 91
        },
        {
          "lastName": "Origi",
          "firstName": "Divock",
          "teamId": "578",
          "kind": "minuteOut",
          "minute": 91
        }
      ],
      "away": []
    },
    {
      "minute": 72,
      "home": [],
      "away": [
        {
          "lastName": "Wondolowski",
          "firstName": "Chris",
          "teamId": "647",
          "kind": "minuteIn",
          "minute": 72
        },
        {
          "lastName": "Zusi",
          "firstName": "Graham",
          "teamId": "647",
          "kind": "minuteOut",
          "minute": 72
        }
      ]
    },
    {
      "minute": 60,
      "home": [
        {
          "lastName": "Mirallas",
          "firstName": "Kevin",
          "teamId": "578",
          "kind": "minuteIn",
          "minute": 60
        },
        {
          "lastName": "Mertens",
          "firstName": "Dries",
          "teamId": "578",
          "kind": "minuteOut",
          "minute": 60
        }
      ],
      "away": []
    },
    {
      "minute": 42,
      "home": [
        {
          "lastName": "Kompany",
          "firstName": "Vincent",
          "teamId": "578",
          "kind": "yellowCard",
          "minute": 42
        }
      ],
      "away": []
    },
    {
      "minute": 32,
      "home": [],
      "away": [
        {
          "lastName": "Yedlin",
          "firstName": "Deandre",
          "teamId": "647",
          "kind": "minuteIn",
          "minute": 32
        },
        {
          "lastName": "Johnson",
          "firstName": "Fabian",
          "teamId": "647",
          "kind": "minuteOut",
          "minute": 32
        }
      ]
    },
    {
      "minute": 18,
      "home": [],
      "away": [
        {
          "lastName": "Cameron",
          "firstName": "Geoff",
          "teamId": "647",
          "kind": "yellowCard",
          "minute": 18
        }
      ]
    }
  ],
  "homeTeam": {
    "id": "578",
    "name": "Belgium",
    "logo": "https://s3.eu-central-1.amazonaws.com/belgianfootball/s3fs-public/rbfa/img/logos/countries/578.png"
  },
  "awayTeam": {
    "id": "647",
    "name": "USA",
    "logo": "https://s3.eu-central-1.amazonaws.com/belgianfootball/s3fs-public/rbfa/img/logos/countries/647.png"
  },
  "outcome": {
    "homeTeamGoals": 2,
    "homeTeamPenaltiesScored": null,
    "awayTeamGoals": 1,
    "awayTeamPenaltiesScored": null,
    "subscript": null,
    "isFinished": true,
    "hasPenalties": false,
    "hasSubscript": false
  },
  "tournament": {
    "ageCategory": "Belgian Red Devils",
    "nameTournament": "Brazil - 2014",
    "qualifyingGroup": "Round of 16",
    "groupCode": null
  },
  "lineup": [
    {
      "home": {
        "id": "5661",
        "lastName": "Courtois",
        "firstName": "Thibaut",
        "shirtNumber": "1",
        "badges": "(GK)",
        "events": []
      },
      "away": {
        "id": "1HowardTim",
        "lastName": "Howard",
        "firstName": "Tim",
        "shirtNumber": "1",
        "badges": "(GK)",
        "events": []
      }
    },
    {
      "home": {
        "id": "3995",
        "lastName": "Alderweireld",
        "firstName": "Toby",
        "shirtNumber": "2",
        "badges": "",
        "events": []
      },
      "away": {
        "id": "3GonzalezOmar",
        "lastName": "Gonzalez",
        "firstName": "Omar",
        "shirtNumber": "3",
        "badges": "",
        "events": []
      }
    },
    {
      "home": {
        "id": "3125",
        "lastName": "Kompany",
        "firstName": "Vincent",
        "shirtNumber": "4",
        "badges": "(C)",
        "events": [
          {
            "type": "yellowCard",
            "minute": 42
          }
        ]
      },
      "away": {
        "id": "4BradleyMichael",
        "lastName": "Bradley",
        "firstName": "Michael",
        "shirtNumber": "4",
        "badges": "",
        "events": []
      }
    },
    {
      "home": {
        "id": "3265",
        "lastName": "Vertonghen",
        "firstName": "Jan",
        "shirtNumber": "5",
        "badges": "",
        "events": []
      },
      "away": {
        "id": "5BeslerMatt",
        "lastName": "Besler",
        "firstName": "Matt",
        "shirtNumber": "5",
        "badges": "",
        "events": []
      }
    },
    {
      "home": {
        "id": "3992",
        "lastName": "Witsel",
        "firstName": "Axel",
        "shirtNumber": "6",
        "badges": "",
        "events": []
      },
      "away": {
        "id": "7BeasleyDamarcus",
        "lastName": "Beasley",
        "firstName": "Damarcus",
        "shirtNumber": "7",
        "badges": "",
        "events": []
      }
    },
    {
      "home": {
        "id": "5455",
        "lastName": "De Bruyne",
        "firstName": "Kevin",
        "shirtNumber": "7",
        "badges": "",
        "events": [
          {
            "type": "goalScored",
            "minute": 93
          }
        ]
      },
      "away": {
        "id": "8DempseyClint",
        "lastName": "Dempsey",
        "firstName": "Clint",
        "shirtNumber": "8",
        "badges": "(C)",
        "events": []
      }
    },
    {
      "home": {
        "id": "3746",
        "lastName": "Fellaini",
        "firstName": "Marouane",
        "shirtNumber": "8",
        "badges": "",
        "events": []
      },
      "away": {
        "id": "11BedoyaAlejandro",
        "lastName": "Bedoya",
        "firstName": "Alejandro",
        "shirtNumber": "11",
        "badges": "",
        "events": [
          {
            "type": "minuteOut",
            "minute": 105
          }
        ]
      }
    },
    {
      "home": {
        "id": "4847",
        "lastName": "Hazard",
        "firstName": "Eden",
        "shirtNumber": "10",
        "badges": "",
        "events": [
          {
            "type": "minuteOut",
            "minute": 111
          }
        ]
      },
      "away": {
        "id": "13JonesJermaine",
        "lastName": "Jones",
        "firstName": "Jermaine",
        "shirtNumber": "13",
        "badges": "",
        "events": []
      }
    },
    {
      "home": {
        "id": "3751",
        "lastName": "Mertens",
        "firstName": "Dries",
        "shirtNumber": "14",
        "badges": "",
        "events": [
          {
            "type": "minuteOut",
            "minute": 60
          }
        ]
      },
      "away": {
        "id": "19ZusiGraham",
        "lastName": "Zusi",
        "firstName": "Graham",
        "shirtNumber": "19",
        "badges": "",
        "events": [
          {
            "type": "minuteOut",
            "minute": 72
          }
        ]
      }
    },
    {
      "home": {
        "id": "130",
        "lastName": "Van Buyten",
        "firstName": "Daniel",
        "shirtNumber": "15",
        "badges": "",
        "events": []
      },
      "away": {
        "id": "20CameronGeoff",
        "lastName": "Cameron",
        "firstName": "Geoff",
        "shirtNumber": "20",
        "badges": "",
        "events": [
          {
            "type": "yellowCard",
            "minute": 18
          }
        ]
      }
    },
    {
      "home": {
        "id": "6348",
        "lastName": "Origi",
        "firstName": "Divock",
        "shirtNumber": "17",
        "badges": "",
        "events": [
          {
            "type": "minuteOut",
            "minute": 91
          }
        ]
      },
      "away": {
        "id": "23JohnsonFabian",
        "lastName": "Johnson",
        "firstName": "Fabian",
        "shirtNumber": "23",
        "badges": "",
        "events": [
          {
            "type": "minuteOut",
            "minute": 32
          }
        ]
      }
    }
  ],
  "substitutes": [
    {
      "home": {
        "id": "3285",
        "lastName": "Vermaelen",
        "firstName": "Thomas",
        "shirtNumber": "3",
        "badges": "",
        "events": []
      },
      "away": {
        "id": "2YedlinDeandre",
        "lastName": "Yedlin",
        "firstName": "Deandre",
        "shirtNumber": "2",
        "badges": "",
        "events": [
          {
            "type": "minuteIn",
            "minute": 32
          }
        ]
      }
    },
    {
      "home": {
        "id": "5035",
        "lastName": "Lukaku",
        "firstName": "Romelu",
        "shirtNumber": "9",
        "badges": "",
        "events": [
          {
            "type": "minuteIn",
            "minute": 91
          },
          {
            "type": "goalScored",
            "minute": 105
          }
        ]
      },
      "away": {
        "id": "6BrooksJohn",
        "lastName": "Brooks",
        "firstName": "John",
        "shirtNumber": "6",
        "badges": "",
        "events": []
      }
    },
    {
      "home": {
        "id": "4351",
        "lastName": "Mirallas",
        "firstName": "Kevin",
        "shirtNumber": "11",
        "badges": "",
        "events": [
          {
            "type": "minuteIn",
            "minute": 60
          }
        ]
      },
      "away": {
        "id": "9JohannssonAron",
        "lastName": "Johannsson",
        "firstName": "Aron",
        "shirtNumber": "9",
        "badges": "",
        "events": []
      }
    },
    {
      "home": {
        "id": "3936",
        "lastName": "Mignolet",
        "firstName": "Simon",
        "shirtNumber": "12",
        "badges": "",
        "events": []
      },
      "away": {
        "id": "10DiskerudMix",
        "lastName": "Diskerud",
        "firstName": "Mix",
        "shirtNumber": "10",
        "badges": "",
        "events": []
      }
    },
    {
      "home": {
        "id": "7442",
        "lastName": "Bossut",
        "firstName": "Sammy",
        "shirtNumber": "13",
        "badges": "",
        "events": []
      },
      "away": {
        "id": "12GuzanBrad",
        "lastName": "Guzan",
        "firstName": "Brad",
        "shirtNumber": "12",
        "badges": "",
        "events": []
      }
    },
    {
      "home": {
        "id": "38",
        "lastName": "Lombaerts",
        "firstName": "Nicolas",
        "shirtNumber": "18",
        "badges": "",
        "events": []
      },
      "away": {
        "id": "14DavisBrad",
        "lastName": "Davis",
        "firstName": "Brad",
        "shirtNumber": "14",
        "badges": "",
        "events": []
      }
    },
    {
      "home": {
        "id": "3329",
        "lastName": "Dembélé",
        "firstName": "Mousa",
        "shirtNumber": "19",
        "badges": "",
        "events": []
      },
      "away": {
        "id": "15BeckermanKyle",
        "lastName": "Beckerman",
        "firstName": "Kyle",
        "shirtNumber": "15",
        "badges": "",
        "events": []
      }
    },
    {
      "home": {
        "id": "7134",
        "lastName": "Januzaj",
        "firstName": "Adnan",
        "shirtNumber": "20",
        "badges": "",
        "events": []
      },
      "away": {
        "id": "16GreenJulian",
        "lastName": "Green",
        "firstName": "Julian",
        "shirtNumber": "16",
        "badges": "",
        "events": [
          {
            "type": "minuteIn",
            "minute": 105
          },
          {
            "type": "goalScored",
            "minute": 107
          }
        ]
      }
    },
    {
      "home": {
        "id": "5855",
        "lastName": "Chadli",
        "firstName": "Nacer",
        "shirtNumber": "22",
        "badges": "",
        "events": [
          {
            "type": "minuteIn",
            "minute": 111
          }
        ]
      },
      "away": {
        "id": "17AltidoreJozy",
        "lastName": "Altidore",
        "firstName": "Jozy",
        "shirtNumber": "17",
        "badges": "",
        "events": []
      }
    },
    {
      "home": {
        "id": "3972",
        "lastName": "Ciman",
        "firstName": "Laurent",
        "shirtNumber": "23",
        "badges": "",
        "events": []
      },
      "away": {
        "id": "18WondolowskiChris",
        "lastName": "Wondolowski",
        "firstName": "Chris",
        "shirtNumber": "18",
        "badges": "",
        "events": [
          {
            "type": "minuteIn",
            "minute": 72
          }
        ]
      }
    },
    {
      "home": null,
      "away": {
        "id": "21ChandlerTimmy",
        "lastName": "Chandler",
        "firstName": "Timmy",
        "shirtNumber": "21",
        "badges": "",
        "events": []
      }
    },
    {
      "home": null,
      "away": {
        "id": "22RimandoNick",
        "lastName": "Rimando",
        "firstName": "Nick",
        "shirtNumber": "22",
        "badges": "",
        "events": []
      }
    }
  ],
  "staffLineup": [
    {
      "home": {
        "lastName": "Wilmots",
        "firstName": "Marc",
        "function": "coach"
      },
      "away": {
        "lastName": "Juergen Klinsmann",
        "firstName": null,
        "function": "coach"
      }
    },
    {
      "home": {
        "lastName": "Borkelmans",
        "firstName": "Vital",
        "function": "coach"
      },
      "away": null
    },
    {
      "home": {
        "lastName": "Lemmens",
        "firstName": "Erwin",
        "function": "coach"
      },
      "away": null
    }
  ]
}